tidycensus/__init__.py
tidycensus/census.py
tidycensus-0.0.9.dist-info/METADATA
tidycensus-0.0.9.dist-info/WHEEL
tidycensus-0.0.9.dist-info/licenses/LICENSE
tidycensus-0.0.9.dist-info/RECORD
