Metadata-Version: 2.4
Name: tidycensus
Version: 0.0.9
Summary: A Python wrapper for the U.S. Census Bureau API.
Project-URL: Homepage, https://github.com/alipatti/tidycensus
Author-email: Alistair Pattison <alistairpattison@gmail.com>
License-Expression: MIT
License-File: LICENSE
Classifier: Operating System :: OS Independent
Classifier: Programming Language :: Python :: 3
Requires-Python: >=3.8
Requires-Dist: joblib
Requires-Dist: polars
Requires-Dist: requests
Requires-Dist: rich
